py_aosmith/__init__.py
py_aosmith/client.py
py_aosmith/exceptions.py
py_aosmith/models.py
py_aosmith/py.typed
py_aosmith/queries.py
py_aosmith-1.0.16.dist-info/METADATA
py_aosmith-1.0.16.dist-info/WHEEL
py_aosmith-1.0.16.dist-info/RECORD
