Metadata-Version: 2.4
Name: py-aosmith
Version: 1.0.16
Summary: A Python client library for A. O. Smith water heaters
License: MIT
Author: Brandon Rothweiler
Author-email: brandonrothweiler@gmail.com
Requires-Python: >=3.10,<4.0
Classifier: License :: OSI Approved :: MIT License
Classifier: Programming Language :: Python :: 3
Classifier: Programming Language :: Python :: 3.10
Classifier: Programming Language :: Python :: 3.11
Classifier: Programming Language :: Python :: 3.12
Classifier: Programming Language :: Python :: 3.13
Classifier: Programming Language :: Python :: 3.14
Requires-Dist: aiohttp (>=3.8.6,<4.0.0)
Requires-Dist: tenacity (>=8.2.3,<10.0.0)
Project-URL: Documentation, https://github.com/bdr99/py-aosmith
Project-URL: Homepage, https://github.com/bdr99/py-aosmith
Project-URL: Repository, https://github.com/bdr99/py-aosmith
